spider3/__init__.py
spider3/__main__.py
spider3/proxy.py
spider3-1.0.2.dist-info/METADATA
spider3-1.0.2.dist-info/WHEEL
spider3-1.0.2.dist-info/top_level.txt
spider3-1.0.2.dist-info/RECORD
