Metadata-Version: 2.1
Name: spider3
Version: 1.0.2
Summary: opener
Home-page: UNKNOWN
Author: hao.liu
Author-email: l.hao.2012@qq.com
License: UNKNOWN
Platform: UNKNOWN
Requires-Python: >=3.7
